{
  "schema": "tt-beamer.p9-hf5-t6-stream-purity-matrix.v1",
  "measuredAt": "2026-04-02T23:01:40.106Z",
  "baseUrl": "http://127.0.0.1:4173",
  "boardCount": 3,
  "matrix": [
    {
      "boardId": "nemesis-board-a",
      "version": 50,
      "alignMode": false,
      "frameHasVisualBlock": true,
      "commandLatencyMs": 3,
      "hasForbiddenTopLevelKey": false,
      "hasForbiddenVisualKey": false,
      "hasLegacyModeField": false,
      "hasLegacyBoardLabel": false,
      "hasLegacyRoomLabel": false,
      "hasServerStreamOverlayText": false
    },
    {
      "boardId": "nemesis-board-b",
      "version": 52,
      "alignMode": false,
      "frameHasVisualBlock": true,
      "commandLatencyMs": 3,
      "hasForbiddenTopLevelKey": false,
      "hasForbiddenVisualKey": false,
      "hasLegacyModeField": false,
      "hasLegacyBoardLabel": false,
      "hasLegacyRoomLabel": false,
      "hasServerStreamOverlayText": false
    },
    {
      "boardId": "nemesis-lockdown-a",
      "version": 55,
      "alignMode": false,
      "frameHasVisualBlock": true,
      "commandLatencyMs": 1,
      "hasForbiddenTopLevelKey": false,
      "hasForbiddenVisualKey": false,
      "hasLegacyModeField": false,
      "hasLegacyBoardLabel": false,
      "hasLegacyRoomLabel": false,
      "hasServerStreamOverlayText": false
    }
  ],
  "streamHealth": {
    "schema": "tt-beamer.final-stream-health.v1",
    "generatedAt": "2026-04-02T23:01:40.105Z",
    "connectedClients": 0,
    "producer": {
      "running": true,
      "watchdogActive": true,
      "composing": false,
      "ticks": 60,
      "lastTickAt": "2026-04-02T23:01:40.105Z",
      "recoveries": 0,
      "latestBroadcastVersion": 59,
      "latestComposeError": null,
      "latestComposeErrorAt": null
    },
    "lastFrameAt": "2026-04-02T23:01:40.105Z",
    "sourceVersion": 59,
    "frameId": 60,
    "msSinceLastFrame": 0,
    "healthy": true
  },
  "pass": true
}
